{
  "title": "The Sword Launcher v1.0.1 en el aire",
  "date": "2026-05-30",
  "tag": "update",
  "summary": "Una actualizacion para la pagina y arreglo de bugs en el launcher.",
  "content": "Hola :D, ya he recibido cierta recepcion despues de compartir el launcher y la pagina web.\n\nCambios en el launcher:\n- Se arregló el label con las versiones entrecortado\n- Se puso la URL del roadmap correcta\n- Ahora el launcher puede ejecutar juegos que no están en las carpetas donde se descargaron\n- Ahora el launcher puede decirte si hay una actualización disponible del propio launcher\n- Se eliminó el botón de partidas de configuración\n- Se mejoró el apartado de partidas, ahora podrás elegir si solo quieres pasar logros, solo partidas, o los dos!\n- Se ha dado prioridad a los usuarios de macOS en esta versión\n- Se ha cambiado la forma en que el launcher maneja la instalación de versiones\n\nCambios en CuriLuchas:\n- (Psst, esto es un secreto... ahora CuriLuchas y todo lo que haga te delatará si cambias de lugar el ejecutable. Pero oye, yo no te conté nada, ¿ok?)",
  "version": "1.0.1",
  "image": "https://url-de-una-imagen.png",
  "game": "The Sword Launcher"
}
